{"schemaVersion":"kfc_portal_schema_v1","generatedAt":"2026-07-24T10:05:20.882010+00:00","type":"object","id":"obj_product_alloydb","item":{"id":"obj_product_alloydb","type":"object","title":"Alloydb","status":"tracking","category":"product","summary":"News value Update timeline; public information only.","updatedAt":"2026-07-22T17:19:47.938948Z","createdAt":"2026-07-22T17:19:47.938948Z","objectType":"product","businessArchetype":"","attentionLevel":"C","strategicPosition":"","strategicThesis":"","updates":[],"facts":[{"fact_id":"fact_0097ef69b8b6082e2205513e","research_object_id":"obj_product_alloydb","fact_category":"product_capability","fact_subject":"vector_search_hnsw_throughput_uplift","statement":"在AlloyDB上，启用HNSW预览版后，AI向量搜索的吞吐量可提升至四倍，且无需修改pgvector代码、旨在降低延迟。","unit":"倍 (times)","currency":"N/A","event_time":"2026-07-22T11:00:00","effective_period":"preview","published_at":"2026-07-22T11:00:00","source_grade":"B","source_url":"https://datacentrenews.uk/story/google-boosts-alloydb-vector-search-with-hnsw-preview","status":"verified_candidate","version":1,"is_current":1,"created_at":"2026-07-22T17:19:47.938948Z","value":"4"}],"html":"<p>尚无正式更新记录。</p>"}}