{"schemaVersion":"kfc_portal_schema_v1","generatedAt":"2026-07-24T10:05:20.882010+00:00","type":"object","id":"obj_product_cnb","item":{"id":"obj_product_cnb","type":"object","title":"Tencent Cloud CNB","status":"tracking","category":"product","summary":"News value Update timeline; public information only.","updatedAt":"2026-07-23T13:46:00.465692Z","createdAt":"2026-07-23T13:46:00.387556Z","objectType":"product","businessArchetype":"","attentionLevel":"C","strategicPosition":"","strategicThesis":"","updates":[{"update_id":"update_4a99b4505a28858391ab1678","research_object_id":"obj_product_cnb","event":"腾讯云CodeBuddy NPC已与腾讯云研发协作平台TAPD打通","event_date":"2026-07-23T18:01:13Z","impact_type":"Ecosystem","before_state":"","after_state":"\"TAPD\"","direction":"NEW_FACTOR","importance":50,"review_status":"fact_confirmed","fact_id":"fact_eaa97745b67ec43b16eb5d3c","evidence_id":"article:news_b818c4e36d91687d1ba8:338c8c6f4b21","created_at":"2026-07-23T13:46:00.465692Z","evidence":{"source_name":"infoq.cn","source_grade":"B","source_url":"https://infoq.cn/article/w6DHDb3QUYPLC1vaU8z1","published_at":"2026-07-23T18:01:13Z","source_quote":"目前，腾讯云CodeBuddy NPC已与腾讯云研发协作平台TAPD打通","locator":"article:news_b818c4e36d91687d1ba8","article_id":"news_b818c4e36d91687d1ba8","verification_status":"quote_verified"}},{"update_id":"update_9090fc1397233d396915e15e","research_object_id":"obj_product_cnb","event":"腾讯云CNB平台每月服务超过10万名开发者","event_date":"2026-07-23T18:01:13Z","impact_type":"Customer","before_state":"","after_state":"10","direction":"NEW_FACTOR","importance":50,"review_status":"fact_confirmed","fact_id":"fact_7aeb93f223b146d0a7071d22","evidence_id":"article:news_b818c4e36d91687d1ba8:1c7e6f8b96c6","created_at":"2026-07-23T13:46:00.416284Z","evidence":{"source_name":"infoq.cn","source_grade":"B","source_url":"https://infoq.cn/article/w6DHDb3QUYPLC1vaU8z1","published_at":"2026-07-23T18:01:13Z","source_quote":"腾讯云CNB平台每月服务超过10万名开发者","locator":"article:news_b818c4e36d91687d1ba8","article_id":"news_b818c4e36d91687d1ba8","verification_status":"quote_verified"}}],"facts":[{"fact_id":"fact_7aeb93f223b146d0a7071d22","research_object_id":"obj_product_cnb","fact_category":"users_customers","fact_subject":"monthly_developer_count","statement":"腾讯云CNB平台每月服务超过10万名开发者","unit":"万开发者/月","currency":"N/A","event_time":"2026-07-23T18:01:13","effective_period":"current","published_at":"2026-07-23T18:01:13","source_grade":"B","source_url":"https://infoq.cn/article/w6DHDb3QUYPLC1vaU8z1","status":"verified_candidate","version":1,"is_current":1,"created_at":"2026-07-23T13:46:00.387556Z","value":10},{"fact_id":"fact_eaa97745b67ec43b16eb5d3c","research_object_id":"obj_product_cnb","fact_category":"partnership_ecosystem","fact_subject":"cnb_tapd_integration","statement":"腾讯云CodeBuddy NPC已与腾讯云研发协作平台TAPD打通","unit":"relationship","currency":"N/A","event_time":"2026-07-23T18:01:13","effective_period":"current","published_at":"2026-07-23T18:01:13","source_grade":"B","source_url":"https://infoq.cn/article/w6DHDb3QUYPLC1vaU8z1","status":"verified_candidate","version":1,"is_current":1,"created_at":"2026-07-23T13:46:00.428636Z","value":"TAPD"}],"html":"<section class='value-change'><h3>腾讯云CodeBuddy NPC已与腾讯云研发协作平台TAPD打通</h3><p><strong>变化方向：</strong>NEW_FACTOR · <strong>重要性：</strong>50</p><p><strong>原状态：</strong>此前未记录</p><p><strong>新状态：</strong><mark>&quot;TAPD&quot;</mark></p><p><strong>证据：</strong><a href='https://infoq.cn/article/w6DHDb3QUYPLC1vaU8z1' target='_blank' rel='noreferrer'>infoq.cn ↗</a></p></section><section class='value-change'><h3>腾讯云CNB平台每月服务超过10万名开发者</h3><p><strong>变化方向：</strong>NEW_FACTOR · <strong>重要性：</strong>50</p><p><strong>原状态：</strong>此前未记录</p><p><strong>新状态：</strong><mark>10</mark></p><p><strong>证据：</strong><a href='https://infoq.cn/article/w6DHDb3QUYPLC1vaU8z1' target='_blank' rel='noreferrer'>infoq.cn ↗</a></p></section>"}}