{"schemaVersion":"kfc_portal_schema_v1","generatedAt":"2026-07-24T04:40:21.933815+00:00","type":"object","id":"obj_product_alexa_plus","item":{"id":"obj_product_alexa_plus","type":"object","title":"Alexa+","status":"tracking","category":"product","summary":"News value Update timeline; public information only.","updatedAt":"2026-07-24T00:54:34.070405Z","createdAt":"2026-07-24T00:54:33.902729Z","objectType":"product","businessArchetype":"","attentionLevel":"C","strategicPosition":"","strategicThesis":"","updates":[{"update_id":"update_55388ee0c332f0147194cf43","research_object_id":"obj_product_alexa_plus","event":"Priceline, Lyft, Headspace, and Virgin Atlantic are among the first companies testing MCP integrations on Alexa+, scheduled for later in the year.","event_date":"2026-07-23T10:14:24Z","impact_type":"Ecosystem","before_state":"","after_state":"\"Priceline, Lyft, Headspace, Virgin Atlantic\"","direction":"NEW_FACTOR","importance":50,"review_status":"fact_confirmed","fact_id":"fact_f5a054c1f2ba922d1b61865a","evidence_id":"article:news_eb46f2bf83dd909db346:2c661dcfa93d","created_at":"2026-07-24T00:54:34.070405Z","evidence":{"source_name":"digitaltrends.com","source_grade":"B","source_url":"https://digitaltrends.com/computing/amazon-just-turned-alexa-into-a-full-blown-app-store","published_at":"2026-07-23T10:14:24Z","source_quote":"Priceline, Lyft, Headspace, and Virgin Atlantic are among the first testing this (later in the year).","locator":"article:news_eb46f2bf83dd909db346","article_id":"news_eb46f2bf83dd909db346","verification_status":"quote_verified"}},{"update_id":"update_f8141aa44edd472a57ca7cd1","research_object_id":"obj_product_alexa_plus","event":"Atom Tickets and Fandango are already building ticket-buying flows around the new Amazon Wallet for Alexa+.","event_date":"2026-07-23T10:14:24Z","impact_type":"Ecosystem","before_state":"","after_state":"\"Atom Tickets, Fandango\"","direction":"NEW_FACTOR","importance":50,"review_status":"fact_confirmed","fact_id":"fact_54f7db82891eed22c799a510","evidence_id":"article:news_eb46f2bf83dd909db346:47a8a10694eb","created_at":"2026-07-24T00:54:34.116998Z","evidence":{"source_name":"digitaltrends.com","source_grade":"B","source_url":"https://digitaltrends.com/computing/amazon-just-turned-alexa-into-a-full-blown-app-store","published_at":"2026-07-23T10:14:24Z","source_quote":"companies like Atom Tickets and Fandango are already building ticket-buying flows around it.","locator":"article:news_eb46f2bf83dd909db346","article_id":"news_eb46f2bf83dd909db346","verification_status":"quote_verified"}},{"update_id":"update_9b92c23a9e104f632689c82d","research_object_id":"obj_product_alexa_plus","event":"At launch, the Alexa+ smart home toolkit supports devices from Bosch, Whirlpool, iRobot, Govee, Yale Home, and Eufy.","event_date":"2026-07-23T10:14:24Z","impact_type":"Ecosystem","before_state":"","after_state":"\"Bosch, Whirlpool, iRobot, Govee, Yale Home, Eufy\"","direction":"NEW_FACTOR","importance":50,"review_status":"fact_confirmed","fact_id":"fact_3a0358ed74ee63cae8cb07da","evidence_id":"article:news_eb46f2bf83dd909db346:58172ca492ca","created_at":"2026-07-24T00:54:33.972987Z","evidence":{"source_name":"digitaltrends.com","source_grade":"B","source_url":"https://digitaltrends.com/computing/amazon-just-turned-alexa-into-a-full-blown-app-store","published_at":"2026-07-23T10:14:24Z","source_quote":"For now, devices from Bosch, Whirlpool, iRobot, Govee, Yale Home, and Eufy are supported.","locator":"article:news_eb46f2bf83dd909db346","article_id":"news_eb46f2bf83dd909db346","verification_status":"quote_verified"}}],"facts":[{"fact_id":"fact_54f7db82891eed22c799a510","research_object_id":"obj_product_alexa_plus","fact_category":"partnership_ecosystem","fact_subject":"amazon_wallet_partners","statement":"Atom Tickets and Fandango are already building ticket-buying flows around the new Amazon Wallet for Alexa+.","unit":"relationship","currency":"N/A","event_time":"2026-07-23T10:14:24","effective_period":"Preview period as of article","published_at":"2026-07-23T10:14:24","source_grade":"B","source_url":"https://digitaltrends.com/computing/amazon-just-turned-alexa-into-a-full-blown-app-store","status":"verified_candidate","version":1,"is_current":1,"created_at":"2026-07-24T00:54:34.086913Z","value":"Atom Tickets, Fandango"},{"fact_id":"fact_3a0358ed74ee63cae8cb07da","research_object_id":"obj_product_alexa_plus","fact_category":"partnership_ecosystem","fact_subject":"supported_device_brands","statement":"At launch, the Alexa+ smart home toolkit supports devices from Bosch, Whirlpool, iRobot, Govee, Yale Home, and Eufy.","unit":"relationship","currency":"N/A","event_time":"2026-07-23T10:14:24","effective_period":"at launch as of article","published_at":"2026-07-23T10:14:24","source_grade":"B","source_url":"https://digitaltrends.com/computing/amazon-just-turned-alexa-into-a-full-blown-app-store","status":"verified_candidate","version":1,"is_current":1,"created_at":"2026-07-24T00:54:33.902729Z","value":"Bosch, Whirlpool, iRobot, Govee, Yale Home, Eufy"},{"fact_id":"fact_f5a054c1f2ba922d1b61865a","research_object_id":"obj_product_alexa_plus","fact_category":"partnership_ecosystem","fact_subject":"mcp_integration_partners","statement":"Priceline, Lyft, Headspace, and Virgin Atlantic are among the first companies testing MCP integrations on Alexa+, scheduled for later in the year.","unit":"relationship","currency":"N/A","event_time":"2026-07-23T10:14:24","effective_period":"later in the year (Preview)","published_at":"2026-07-23T10:14:24","source_grade":"B","source_url":"https://digitaltrends.com/computing/amazon-just-turned-alexa-into-a-full-blown-app-store","status":"verified_candidate","version":1,"is_current":1,"created_at":"2026-07-24T00:54:33.998338Z","value":"Priceline, Lyft, Headspace, Virgin Atlantic"}],"html":"<section class='value-change'><h3>Priceline, Lyft, Headspace, and Virgin Atlantic are among the first companies testing MCP integrations on Alexa+, scheduled for later in the year.</h3><p><strong>变化方向：</strong>NEW_FACTOR · <strong>重要性：</strong>50</p><p><strong>原状态：</strong>此前未记录</p><p><strong>新状态：</strong><mark>&quot;Priceline, Lyft, Headspace, Virgin Atlantic&quot;</mark></p><p><strong>证据：</strong><a href='https://digitaltrends.com/computing/amazon-just-turned-alexa-into-a-full-blown-app-store' target='_blank' rel='noreferrer'>digitaltrends.com ↗</a></p></section><section class='value-change'><h3>Atom Tickets and Fandango are already building ticket-buying flows around the new Amazon Wallet for Alexa+.</h3><p><strong>变化方向：</strong>NEW_FACTOR · <strong>重要性：</strong>50</p><p><strong>原状态：</strong>此前未记录</p><p><strong>新状态：</strong><mark>&quot;Atom Tickets, Fandango&quot;</mark></p><p><strong>证据：</strong><a href='https://digitaltrends.com/computing/amazon-just-turned-alexa-into-a-full-blown-app-store' target='_blank' rel='noreferrer'>digitaltrends.com ↗</a></p></section><section class='value-change'><h3>At launch, the Alexa+ smart home toolkit supports devices from Bosch, Whirlpool, iRobot, Govee, Yale Home, and Eufy.</h3><p><strong>变化方向：</strong>NEW_FACTOR · <strong>重要性：</strong>50</p><p><strong>原状态：</strong>此前未记录</p><p><strong>新状态：</strong><mark>&quot;Bosch, Whirlpool, iRobot, Govee, Yale Home, Eufy&quot;</mark></p><p><strong>证据：</strong><a href='https://digitaltrends.com/computing/amazon-just-turned-alexa-into-a-full-blown-app-store' target='_blank' rel='noreferrer'>digitaltrends.com ↗</a></p></section>"}}