{"schemaVersion":"kfc_portal_schema_v1","generatedAt":"2026-07-21T12:05:16.636313+00:00","type":"news","id":"cand-candidate_6fffa5e85ecf22ebd70960f5","item":{"id":"cand-candidate_6fffa5e85ecf22ebd70960f5","type":"news","title":"Show HN：人工智能秘书——“以防万一”停止检查你的手机","sourceId":"github.com","status":"new","publishedAt":"2026-07-21T08:50:41","updatedAt":"2026-07-21T06:05:12.097080Z","summary":"文章网址：https://github.com/mathigatti/telegram-ai-secretary 评论网址：https://news.ycombinator.com/item?id=48986826 积分：1 # 评论：0","articleId":"","url":"https://github.com/mathigatti/telegram-ai-secretary"}}