{"schemaVersion":"kfc_portal_schema_v1","generatedAt":"2026-07-21T12:10:35.113167+00:00","type":"news","id":"cand-candidate_0484774f1745f3bf9c7321ac","item":{"id":"cand-candidate_0484774f1745f3bf9c7321ac","type":"news","title":"【半导体材料概念持续调整 有研硅触及跌停】","sourceId":"cls.cn","status":"new","publishedAt":"2026-07-21T09:02:04","updatedAt":"2026-07-21T04:04:58.957988Z","summary":"财联社7月21日电，半导体材料概念持续调整，有研硅触及20cm跌停，此前格林达4连跌停，争光股份、中船特气跌超10%，和远气体、华特气体跌幅靠前。 Delivered by PolitePaul service","articleId":"","url":"https://cls.cn/detail/2432090"}}