{"schemaVersion":"kfc_portal_schema_v1","generatedAt":"2026-07-21T23:00:34.256674+00:00","type":"news","id":"cand-candidate_a82fc19bb0232f58a2d64531","item":{"id":"cand-candidate_a82fc19bb0232f58a2d64531","type":"news","title":"暴雨和洪涝威胁纽约市早晚高峰交通","sourceId":"bloomberg.com","status":"new","publishedAt":"2026-07-21T23:08:08","updatedAt":"2026-07-21T15:42:50.310824Z","summary":"New York City Rush Hour Threatened by Heavy Rain, Flooding","articleId":"","url":"https://bloomberg.com/news/articles/2026-07-21/new-york-city-rush-hour-threatened-by-heavy-rain-flooding"}}