{"schemaVersion":"kfc_portal_schema_v1","generatedAt":"2026-07-21T21:20:02.396262+00:00","type":"news","id":"cand-candidate_a13734b3691f8e67a230a2fa","item":{"id":"cand-candidate_a13734b3691f8e67a230a2fa","type":"news","title":"坐拥300万粉丝的澳洲网红\"Lily Jay\"被揭完全由AI合成，伪造孤儿院行善骗局暴露，AI造假引发关注","sourceId":"mp.weixin.qq.com","status":"new","publishedAt":"2026-07-21T22:02:26","updatedAt":"2026-07-21T16:26:02.816265Z","summary":"坐拥300万粉丝的澳洲网红\"Lily Jay\"被揭完全由AI合成，伪造孤儿院行善骗局暴露，AI造假引发关注。","articleId":"","url":"http://mp.weixin.qq.com/s?__biz=MzI3MTA0MTk1MA%3D%3D&chksm=f0e6bf435ab6cc40f7c7a38794b458952f70344f2506f08fe72e641084e8dcf0373f244cdc2b&idx=2&mid=2652714192&sn=e24f5e6cbb82f1b5a75572d93e18093d"}}