{"schemaVersion":"kfc_portal_schema_v1","generatedAt":"2026-07-21T17:51:44.328735+00:00","type":"news","id":"cand-candidate_22ecdc1817210e2c050999a6","item":{"id":"cand-candidate_22ecdc1817210e2c050999a6","type":"news","title":"Skyfall plans to buy a small business for an AI CEO test","sourceId":"runtimewire.com","status":"new","publishedAt":"2026-07-21T21:00:48","updatedAt":"2026-07-21T14:18:07.383500Z","summary":"Article URL: https://runtimewire.com/article/skyfall-ai-buy-business-test-ai-ceo Comments URL: https://news.ycombinator.com/item?id=48991778 Points: 1 # Comments: 0","articleId":"","url":"https://runtimewire.com/article/skyfall-ai-buy-business-test-ai-ceo"}}