{"schemaVersion":"kfc_portal_schema_v1","generatedAt":"2026-07-21T23:14:17.258595+00:00","type":"news","id":"cand-candidate_a4ea2ed2d897f3b9499ac660","item":{"id":"cand-candidate_a4ea2ed2d897f3b9499ac660","type":"news","title":"美股光通信板块盘初全线上涨 Coherent涨近7%","sourceId":"api3.cls.cn","status":"new","publishedAt":"2026-07-21T22:21:25","updatedAt":"2026-07-21T15:06:09.750746Z","summary":"美股光通信板块盘初全线上涨 Coherent涨近7%","articleId":"","url":"https://api3.cls.cn/share/article/2433065?app=&os=web&sv=7.7.5"}}