{"schemaVersion":"kfc_portal_schema_v1","generatedAt":"2026-07-21T22:33:58.501113+00:00","type":"news","id":"cand-candidate_6c81f7d1728d4d26f0cc72ba","item":{"id":"cand-candidate_6c81f7d1728d4d26f0cc72ba","type":"news","title":"加密银行 Augustus 完成 1.8 亿美元融资，估值达 10 亿美元","sourceId":"techflowpost.com","status":"new","publishedAt":"2026-07-21T23:00:39","updatedAt":"2026-07-21T15:06:09.750746Z","summary":"加密银行 Augustus 完成 1.8 亿美元融资，估值达 10 亿美元","articleId":"","url":"https://techflowpost.com/newsletter/detail_129056.html"}}