{"schemaVersion":"kfc_portal_schema_v1","generatedAt":"2026-07-24T04:27:15.542010+00:00","type":"news","id":"cand-candidate_14a1ce31324cd4c196f52d2b","item":{"id":"cand-candidate_14a1ce31324cd4c196f52d2b","type":"news","title":"BNEF 将美国数据中心电力需求预测提高了近一倍","sourceId":"latitudemedia.com","status":"selected_for_digest","publishedAt":"2026-07-22T02:26:35","updatedAt":"2026-07-22T01:29:05.037804Z","summary":"尽管存在当地反对等发展风险，但 2035 年的前景自 12 月以来增长了 83%。 BNEF 将美国数据中心电力需求预测提高了近一倍，该消息首先出现在 Latitude Media 上。","articleId":"","url":"https://latitudemedia.com/news/bnef-nearly-doubled-its-forecast-for-us-data-center-power-demand"}}