{"schemaVersion":"kfc_portal_schema_v1","generatedAt":"2026-07-21T16:40:02.122908+00:00","type":"news","id":"cand-candidate_79dd49dab5938327244a58b3","item":{"id":"cand-candidate_79dd49dab5938327244a58b3","type":"news","title":"UK Government Puts AI at Cabinet Level as DSIT Is Dissolved, Raising Questions For Quantum Strategy","sourceId":"thequantuminsider.com","status":"new","publishedAt":"2026-07-21T23:13:21","updatedAt":"2026-07-21T16:36:14.146525Z","summary":"Insider Brief The U.K. government has elevated artificial intelligence to the center of policymaking by giving its AI minister a seat in Cabinet while abolishing the Department for Science, Innovation and Technology, a restructuring that could have important implications for Britain’s quantum technology ambitions. According to the BBC, Prime Minister Andy Burnham has dismantled the […]","articleId":"","url":"https://thequantuminsider.com/2026/07/21/uk-government-puts-ai-at-cabinet-level-as-dsit-is-dissolved-raising-questions-for-quantum-strategy"}}