{"schemaVersion":"kfc_portal_schema_v1","generatedAt":"2026-07-21T15:09:42.466418+00:00","type":"news","id":"cand-candidate_53d057fb6ccc729cdeb9f548","item":{"id":"cand-candidate_53d057fb6ccc729cdeb9f548","type":"news","title":"Show HN: Ripple – Rust Pusher-compatible WebSocket server, a drop-in Reverb swap","sourceId":"github.com","status":"new","publishedAt":"2026-07-21T20:33:12","updatedAt":"2026-07-21T13:47:02.580733Z","summary":"Article URL: https://github.com/madisoheib/Ripple Comments URL: https://news.ycombinator.com/item?id=48991497 Points: 2 # Comments: 0","articleId":"","url":"https://github.com/madisoheib/Ripple"}}