{"schemaVersion":"kfc_portal_schema_v1","generatedAt":"2026-07-24T04:40:21.933815+00:00","type":"news","id":"cand-candidate_0608d50e9ca72267fbfac0a0","item":{"id":"cand-candidate_0608d50e9ca72267fbfac0a0","type":"news","title":"稳定币非中美博弈合适武器：分析认为在中美竞争中，稳定币并非合适的金融武器","sourceId":"bloomberg.com","status":"new","publishedAt":"2026-07-22T04:11:30","updatedAt":"2026-07-21T20:24:58.383040Z","summary":"稳定币非中美博弈合适武器：分析认为在中美竞争中，稳定币并非合适的金融武器。","articleId":"","url":"https://bloomberg.com/opinion/articles/2026-07-21/stablecoin-is-the-wrong-weapon-in-us-china-fight"}}