{"schemaVersion":"kfc_portal_schema_v1","generatedAt":"2026-07-24T15:15:28.920584+00:00","type":"news","id":"cand-candidate_3c49a9f2bda013533cda1d43","item":{"id":"cand-candidate_3c49a9f2bda013533cda1d43","type":"news","title":"印度增长依然强劲，但贸易壁垒威胁2047年目标：世贸组织","sourceId":"timesofindia.indiatimes.com","status":"new","publishedAt":"2026-07-22T01:38:26","updatedAt":"2026-07-22T01:07:20.661395Z","summary":"印度的经济持续强劲增长，但需要进行结构性改革才能达到发达国家地位。高贸易成本和监管复杂性给全球一体化带来了重大挑战。世界贸易组织的报告指出了贸易便利化和金融包容性方面的进展。印度正在积极寻求自由贸易协定以推动其出口战略。实现全球出口的更大份额需要平衡自力更生，更加开放。","articleId":"","url":"https://timesofindia.indiatimes.com/business/india-business/indias-growth-remains-strong-but-trade-barriers-threaten-2047-goal-wto/articleshow/132542403.cms"}}