{"schemaVersion":"kfc_portal_schema_v1","generatedAt":"2026-07-21T17:51:44.328735+00:00","type":"news","id":"cand-candidate_e226af493cf613a5b61ecc72","item":{"id":"cand-candidate_e226af493cf613a5b61ecc72","type":"news","title":"美股异动｜绩优股3M升逾8%、诺华升3%，MSCI绩后暴跌10%，NEBIUS上涨7%，台积电上涨4%","sourceId":"laohu8.com","status":"new","publishedAt":"2026-07-21T21:11:11","updatedAt":"2026-07-21T14:06:18.370768Z","summary":"Delivered by PolitePaul service","articleId":"","url":"https://laohu8.com/news/1146321956"}}