{"schemaVersion":"kfc_portal_schema_v1","generatedAt":"2026-07-21T09:28:33.664175+00:00","type":"news","id":"news_ba92a1af94045b442216","item":{"id":"news_ba92a1af94045b442216","type":"news","title":"英伟达推出合成视频检测器 NIM：逐帧揪出 AI 生成视频，准确率可达 92%","sourceId":"ithome.com","status":"watch_only","publishedAt":"2026-07-21T15:37:36","updatedAt":"2026-07-21T09:17:13.951678Z","summary":"IT之家 7 月 21 日消息，英伟达现已推出合成视频检测器 NIM（Synthetic Video Detector NIM）服务，可逐帧分析出 AI 生成的视频， 准确率最高可达 92% 。 据介绍，这项工具面向媒体机构、新闻编辑部和个人用户，能够逐帧分析视频，并使用分类评分判断视频是否包含 AI 生成内容。 据英伟达内部测试结果，NIM 对无压缩视频的检测准确率可达 92%；15% 压缩率视频准确率为 85%；50% 压缩率视频准确率则为 82%。测试结果表明，即使在现代视频编码、压缩带来各种伪影的情况下，该工具依然能较为准确地识别 AI 视频。 同时，这项技术可以在 RTX GPU 系统（具体型号官方未注明）上，以最快 22 毫秒的速度分析一段 1080P 视频；而在企业数据中心 GPU L40（IT之家注：Ada Lovelace 架构）上，处理时间约为 30 毫秒。","articleId":"","url":"https://ithome.com/0/979/594.htm"}}