{"schemaVersion":"kfc_portal_schema_v1","generatedAt":"2026-07-24T15:05:16.632572+00:00","type":"news","id":"news_c3af78b319a2295a233d","item":{"id":"news_c3af78b319a2295a233d","type":"news","title":"印度活动家旺楚克结束为期26天的绝食抗议，「蟑螂」示威者誓言继续抗争","sourceId":"npr.org","status":"new","publishedAt":"2026-07-24T13:56:15","updatedAt":"2026-07-24T09:30:25.260633Z","summary":"印度活动家索南·旺楚克周五结束了为期26天的绝食抗议，该行动激发了一场青年运动，使其成为近年来印度最大规模的抗议之一，但示威者誓言将继续抗议，直至教育部长辞职。","articleId":"","url":"https://npr.org/2026/07/24/nx-s1-5906236/india-wangchuk-hunger-strike-cockroach-protesters"}}