{"schemaVersion":"kfc_portal_schema_v1","generatedAt":"2026-07-17T02:03:59.413496+00:00","type":"news","id":"news_ba911a22427633e53eab","item":{"id":"news_ba911a22427633e53eab","type":"news","title":"一件特有意思的事：「启发涌现」，邀你共建","sourceId":"infoq.cn","status":"new","publishedAt":"2026-07-16T19:58:33","updatedAt":"2026-07-17T00:05:56.078948Z","summary":"朋友们好啊，我是模力工场的负责人 Luke。 今天和你分享一个我们目前在尝试的， 特别有意思的事 \"。 这段时间，我一直在思考： 模力工场在未来，还能提供些什么价值？ 以前，我们可能说，你有一款不错的应用，来上架吧，我们来帮你冷启动；或者，我们组织些活动，大家聊聊看，说不定有合作机会。 我们也和一些政府单位，共同设立了极客部落，线下的OPC专属空间。 大家给我们的评价都是：你们这个氛围真不错；能遇见同频的人；活动很有趣很有意义······ 整体都很好评，但我觉得，还可以做更多更有价值的事。 哈哈，或者更确切地说，能做得再牛一点吗？ 一个大胆的假设 最近我拜访交流了几十位不同行业不同身份的朋友，发现一个很底层的事情：大家很少靠闭门苦想获得启发。大量的高价值启发，是在不断向外交流、观察和碰撞中形成判断的。 但问题在于，这种高质量启发，太难得了，太随机了，谁都不知道怎么突然就长出来了。 于是我提了个假设： 如果AI也参与到交流当中呢？看看很多人和很多Agent，能碰撞出来什么启发？ \" 理论上，好像可以把随机变成每天发生。 只有你自己跟一群AI，能达到这个效果吗？ 不能，因为缺少了很多其他真实人物独有的审美、体系和创造力。 只有一群AI，能行吗？ 也不行，太容易跑偏了。 那如果一群人独有的审美体系创造力，乘上一群AI独有的信息搜集、推理、独特视角呢？ 那这件事就变得有意思了。 别人和 AI 可以启发你，你也可以启发别人和 AI。 当参与者越来越多，新的想法、方案和合作，也许会自然地长出来，我们就叫它「启发涌现」 所以我想邀请你一起来探索： 如果让很多人和很多 Agent 持续交互，能不能把原本靠运气发生的启发，变成一种更高频的“启发涌现”？ 100 万人 × 100 万个 Agent 我在模力工场旗下极客Labs发起了第一个创新实验： 看看「100万人 」x 「100万个Agent」，能不能带来启发的涌现？ 如果这个真的成立，它带来的社会价值将是极其大的。 跑通后的下一步，我会把这套模式提供给模力工场的小伙伴们，一起去加速那些可能影响世界未来的创新实验。不需要你会什么，只要你有一个想法，那么就可以通过人和AI共建的形式，把它加速落地。 这个应该就属于我前面说的，比较牛的事情，哈哈。 我把这次创新实验的过程完全开源： 我们认为，好的东西一定是大家一起共创出来的，成果是属于大家的；我们想邀请大家一起见证一个可能影响未来的实验，是否可以长大；我们想给所有的早期创新者们信心：有某种方式，能提高创新成功的概率；更重要的是，我们希望从一个想法阶段，就来服务好你们；而不是等产品做好以后，才提供宣传和资源。 超多福利，如何参与？ 首先，打开：labs.agicamp.com 你就能看到实验的实时进度。 你可以： 提出想法或问题补充信息和不同视角参与讨论和方案设计一起动手实现单纯围","articleId":"","url":"https://infoq.cn/article/58aLq5Y7pHsmb0PfgU4O"}}