{"schemaVersion":"kfc_portal_schema_v1","generatedAt":"2026-07-24T07:05:19.939091+00:00","type":"news","id":"news_a00a05e491fde50ab894","item":{"id":"news_a00a05e491fde50ab894","type":"news","title":"福特F-150现兼作售价1100美元的家庭备用发电机","sourceId":"fortune.com","status":"new","publishedAt":"2026-07-24T00:34:03","updatedAt":"2026-07-23T19:02:25.237291Z","summary":"电动车销量同比下滑23.8%，福特、通用、起亚和特斯拉等车企纷纷进军家用能源领域以寻求新收入。","articleId":"","url":"https://fortune.com/2026/07/23/ford-f150-home-backup-power-ev-energy-pivot"}}