{"schemaVersion":"kfc_portal_schema_v1","generatedAt":"2026-07-24T15:05:16.632572+00:00","type":"news","id":"news_fdde4a29966388755d7e","item":{"id":"news_fdde4a29966388755d7e","type":"news","title":"猴王Bang：统一的科学多模态基础模型","sourceId":"arxiv.org","status":"new","publishedAt":"2026-07-24T12:00:00","updatedAt":"2026-07-24T05:31:02.451571Z","summary":"科学发现正从单一学科向多领域推理转变，科学AI也面临类似转型。现有系统或专注于单一领域，或主要通过文本标记和提示接口统一科学数据，难以处理多样化科学输入、生成模态原生输出并支持跨领域联合理解、推理与生成。本文提出MKB，一个以共享Transformer骨干和模态定制编码器、适配器、解码器为核心的统科学多模态理解与生成模型，覆盖DNA、RNA、蛋白质、小分子、地球科学和医学图像六个分支，支持生物序列、分子字符串、气象场和分割掩膜等原生输出。","articleId":"","url":"https://arxiv.org/abs/2607.20557"}}