{"schemaVersion":"kfc_portal_schema_v1","generatedAt":"2026-07-24T01:37:53.525612+00:00","type":"news","id":"news_da436a4975ac628a89a8","item":{"id":"news_da436a4975ac628a89a8","type":"news","title":"Qedma将量子纠错抑制软件与Quantinuum平台完成集成","sourceId":"thequantuminsider.com","status":"new","publishedAt":"2026-07-23T20:06:33","updatedAt":"2026-07-23T22:49:59.357242Z","summary":"量子软件公司Qedma宣布与Quantinuum平台完成集成，使用户可在其业界领先的量子计算硬件上运行先进的纠错抑制技术。该技术集成由Qedma作为Quantinuum初创合作伙伴计划创始成员，历时一年完成，其量子纠错抑制与增强方案在多种应用中表现优异。","articleId":"","url":"https://thequantuminsider.com/2026/07/23/qedma-error-mitigation-software-quantinuum-platform"}}