{"schemaVersion":"kfc_portal_schema_v1","generatedAt":"2026-07-24T09:05:25.106882+00:00","type":"news","id":"news_6c9b4a018a1f3926f626","item":{"id":"news_6c9b4a018a1f3926f626","type":"news","title":"独家丨华为22年老兵从AI终局倒推LPU，元川微完成新一轮数亿元融资","sourceId":"leiphone.com","status":"new","publishedAt":"2026-07-24T10:23:00","updatedAt":"2026-07-24T07:01:08.471038Z","summary":"雷峰网独家获悉，LPU创业公司元川微已完成Pre-A轮数亿元融资，由IDG资本领投，孚腾资本、九坤创投、尚颀资本、顺禧基金、徐汇科创投跟投。这是元川微2026年以来完成的第四轮融资，创始人杨滨为华为22年老兵，曾赴美组建华为处理器团队。资金将用于LPU+芯片研发、软件生态建设及产品工程化推进。杨滨表示，创业是对过去资源积累的兑现，其目标是围绕Agent时代重新组织推理计算。CTO孙博士深耕高性能计算架构超三十年，首席软件工程师Will博士拥有20余年编译器及异构系统软件经验。","articleId":"","url":"https://leiphone.com/category/chips/AGaAOgr50XhElaxq.html"}}