{"schemaVersion":"kfc_portal_schema_v1","generatedAt":"2026-07-20T16:19:21.343449+00:00","type":"news","id":"news_95a8972adbfe03b54656","item":{"id":"news_95a8972adbfe03b54656","type":"news","title":"DataBuff v0.1.4 发布 · 7 大 AI 运维能力","sourceId":"oschina.net","status":"new","publishedAt":"2026-07-20T09:34:15","updatedAt":"2026-07-20T16:07:18.695626Z","summary":"DataBuff 是一款面向云原生与微服务场景的开源 AI Native OpenTelemetry APM，采用 OTLP 标准接入、Apache Doris 统一存储、Web Platform 提供拓扑 / Trace / 指标与多 Agent 排障能力。项目已在 OSCHINA 软件库收录，软件主页：https://www.oschina.net/p/databuff 今天，DataBuff 正式发布 v0.1.4（2026-07-19）。相对...","articleId":"","url":"https://oschina.net/news/474811/databuff-0-1-4-released"}}