{"schemaVersion":"kfc_portal_schema_v1","generatedAt":"2026-07-24T07:05:19.939091+00:00","type":"news","id":"news_72c10df13966621d3cb2","item":{"id":"news_72c10df13966621d3cb2","type":"news","title":"美银：智能体 CPU 标准之争，英伟达“更快”vs AMD“更多”","sourceId":"techflowpost.com","status":"new","publishedAt":"2026-07-24T11:32:29","updatedAt":"2026-07-24T05:21:11.387190Z","summary":"美银 7 月 22 日报告指出，英伟达与 AMD 在智能体 CPU 领域正展开一场定义战。英伟达上周发布 Vera CPU 架构，88 个定制 ARM 核心，1.2TB/s 内存带宽，主张单核性能决定智能体响应速度；AMD 则强调 EPYC 9965 在并发吞吐量上更具优势。美银维持英伟达和 AMD 买入评级，目标价分别为 350 美元和 620 美元。","articleId":"","url":"https://techflowpost.com/newsletter/detail_129364.html"}}