{"schemaVersion":"kfc_portal_schema_v1","generatedAt":"2026-07-20T11:46:05.910301+00:00","type":"news","id":"news_d13a975f7c44820eeb89","item":{"id":"news_d13a975f7c44820eeb89","type":"news","title":"全球首发2nm骁龙8E6 Pro！小米18系列真要提前发布了 提前两个月登陆印度","sourceId":"163.com","status":"new","publishedAt":"2026-07-20T14:35:05","updatedAt":"2026-07-20T10:58:53.918344Z","summary":"快科技7月20日消息，此前产业链供应链就曾传出小米18系列可能将打破以往发布节奏提前登场的消息，目前最新流出的多方信息证实，该爆料的可信度已经非常高。 按照之前曝光的产品节奏规划，小米18系列会在今年9月率先面向中国市场正式亮相发布，这款新机将作为首发机型，搭载高通下一代旗舰处理器骁龙8 Elite Gen6系列。 如今这个首发信息已经得到进一步佐证。 根据印度当地科技媒体的最新报道，小米18系列手机预计今年12月正式登陆印度市场，这个开卖节点比小米过往旗舰的印度上市时间提前了整整两个月，目的就是为了抢占当地年末冬季的换机市场红利。 值得注意的是，不少产业链内部消息显示，小米18系列这次首发阶段将只推出小米18 Pro和小米18 Pro Max两款高配机型，定位基础款的标准版机型会稍晚上市，这套发布节奏和苹果iPhone 18系列的规划十分相似，都选择优先推出定位更高的Pro系列型号投放市场。 核心性能层面，小米18系列首发的骁龙8 Elite Gen6 Pro芯片，采用台积电N2P改良版2nm GAA工艺打造，晶体管密度相比上代旗舰搭载的3nm工艺芯片提升30%，整机的功耗控制表现、长时间高负载下的持续性能释放都得到了显著优化。 这款全新旗舰芯片采用第三代Oryon架构的2+3+3三丛集八核CPU配置，搭配16MB超大二级缓存，同时整合Adreno 850 GPU以及18MB专属图形缓存，原生支持LPDDR6高速内存，端侧AI算力、光追游戏表现、本地运行大模型的能力都刷新了当前消费级手机芯片的历史纪录。 特别声明：以上内容(如有图片或视频亦包括在内)为自媒体平台“网易号”用户上传并发布，本平台仅提供信息存储服务。 Notice: The content above (including the pictures and videos if any) is uploaded and posted by a user of NetEase Hao, which is a social media platform and only provides information storage services.","articleId":"","url":"https://163.com/dy/article/L29O4S8F0511CPVM.html"}}