{"schemaVersion":"kfc_portal_schema_v1","generatedAt":"2026-07-24T18:05:17.098898+00:00","type":"news","id":"news_0b3248304910f8e260dd","item":{"id":"news_0b3248304910f8e260dd","type":"news","title":"直捣企业出海系统性难题，飞书深诺发布Marvy2.0接管决策和执行","sourceId":"leiphone.com","status":"new","publishedAt":"2026-07-24T18:25:00","updatedAt":"2026-07-24T16:40:31.828005Z","summary":"2026年7月23日，在第十届全球跨境电商峰会暨2026全球化新品牌AI竞争力大会上，AI全球营销科技平台飞书深诺Meetsocial正式发布新一代企业级出海营销AgentOS——Marvy 2.0，定位为「全球AI营销新基建」。大会现场，飞书深诺与BytePlus达成官方合作，Marvy 2.0将接入BytePlus大模型体系与Seedance音视频生成能力。IDC白皮书显示，出海营销AI应用率已达78.5%，但多数企业仍处于L1阶段，仅飞书深诺等极个别企业达到L3等级，结构性失衡严重。","articleId":"","url":"https://leiphone.com/category/industrynews/urzkJ71nAWLXBAFT.html"}}