{"schemaVersion":"kfc_portal_schema_v1","generatedAt":"2026-07-20T11:39:16.029791+00:00","type":"news","id":"news_e36d164dfa44f4d4b52e","item":{"id":"news_e36d164dfa44f4d4b52e","type":"news","title":"中软国际与月之暗面签署协议，达成 Token 分成及联合创新合作","sourceId":"ithome.com","status":"selected_for_digest","publishedAt":"2026-07-20T15:52:49","updatedAt":"2026-07-20T10:26:31.494257Z","summary":"IT之家 7 月 20 日消息，中软国际今日发布公告，近日，公司已与北京月之暗面科技有限公司（以下简称“月之暗面”）正式签署“登月计划”之 Token 分成及联合创新合作协议 ，此举是公司面向高专业价值 Token 运营商转型的关键战略举措。 据介绍，本次合作中，中软国际充分发挥自身在企业服务领域深厚的场景积累、行业 knowhow 及规模化落地交付能力，以及行业及代码生成与开发工程（coding）实践能力；月之暗面依托其在通用大模型领域领先的算法体系与前沿技术研发能力，形成强强协同、优势互补的合作格局。双方将以中软国际自主研发的企业智能操作系统 AllMeta 平台 + 月之暗面 K2.7 Code 及 K3 模型及后续迭代版本 为核心技术底座，共同推进企业级智能体技术、产品与解决方案在 能源电力、金融等 行业的创新及规模化商用。 双方将共建 FDE 创新实验室，集结顶尖行业专家与技术研发力量，共同开展企业级 Agent 产品的定义、研发、交付、打磨、测试与持续迭代。首期合作将优先聚焦能源电力关键行业，围绕行业核心业务场景开展技术攻关与场景创新。 月之暗面将为该公司提供大模型技术支撑 ，助力能源电力等关键基础行业的专属知识库建设、模型微调与定制化训练，联合打造智能电力 AOS、行业专属智能体及一体化数智解决方案。在专有云部署方面， 双方将长期共同推进国产算力适配与兼容改造 ，确保关键基础设施自主可控。 同时，双方将在品牌共建、标杆案例打造、行业生态拓展及人才队伍建设等方面深度协同，共同扩大行业影响力，加速推进 Agentic AI 在关键行业的落地普及。 商业模式方面，双方将探索落地中国版“模型 + 企业服务”协同新范式， 采用 Token 分成机制 实现共赢发展。针对合作落地过程中基于 Kimi 大模型产生的 Token 消耗收益及其他合作衍生收入， 双方将按照协议约定比例进行分成 。此外，该公司将全力推进算力业务布局，自建行业算力中心将优先满足月之暗面的算力需求。","articleId":"","url":"https://ithome.com/0/979/065.htm"}}