{"schemaVersion":"kfc_portal_schema_v1","generatedAt":"2026-07-21T07:29:36.835001+00:00","type":"news","id":"news_4e0754625ee0a1c333ae","item":{"id":"news_4e0754625ee0a1c333ae","type":"news","title":"NVIDIA Agent Toolkit 通过新的 Omniverse 库进行扩展，让 AI 代理能够构建模拟就绪的世界","sourceId":"nvidianews.nvidia.com","status":"new","publishedAt":"2026-07-20T23:00:00","updatedAt":"2026-07-20T23:40:02.732912Z","summary":"","articleId":"","url":"https://nvidianews.nvidia.com/news/nvidia-agent-toolkit-expands-with-new-omniverse-libraries-putting-ai-agents-to-work-building-simulation-ready-worlds"}}