{"schemaVersion":"kfc_portal_schema_v1","generatedAt":"2026-07-16T13:25:08.804347+00:00","type":"news","id":"news_de0d0b160d924aa0bcbe","item":{"id":"news_de0d0b160d924aa0bcbe","type":"news","title":"苹果 AI 用起来怎么样？我们用美版 iPhone 提前试了试","sourceId":"mp.weixin.qq.com","status":"new","publishedAt":"2026-07-15T22:02:26","updatedAt":"2026-07-15T23:32:58.002508Z","summary":"","articleId":"","url":"http://mp.weixin.qq.com/s?__biz=MjgzMTAwODI0MA%3D%3D&chksm=9ae7e7b56f1cdc7fd3aa6c4cb4580af97da5dd9425057b4392d1fe916d9d065f26b2abe62a51&idx=1&mid=2652457349&sn=eb498c0c47bfb930e87dd25a5b08cd0b"}}