{"schemaVersion":"kfc_portal_schema_v1","generatedAt":"2026-07-18T09:27:29.240679+00:00","type":"news","id":"news_2b37c87ce9b2a1074c47","item":{"id":"news_2b37c87ce9b2a1074c47","type":"news","title":"GOAI 世界人工智能开源大赛官网上线，全球报名正式开启","sourceId":"infoq.cn","status":"new","publishedAt":"2026-07-17T19:11:20","updatedAt":"2026-07-18T08:57:11.753393Z","summary":"从杭州出发，面向全球 AI Builders，寻找可运行、可验证、可共建的下一代 AI 创新项目 2026 年 7 月 16 日，GOAI 世界人工智能开源大赛（Global Open-source AI Challenge）官方网站 https://goaihz.com/ \"正式上线，报名通道面向全球开放。 GOAI 世界人工智能开源大赛（以下简称“大赛”）由杭州市开源人工智能基金会主办，Agentic AI Foundation（AAIF）和LF AI & Data Foundation作为全球开源合作伙伴参与支持，并由之江实验室、阿里云智能集团、蚂蚁科技集团股份有限公司、杭州智加未来科技有限公司、云深处科技股份有限公司、杭州群核信息技术有限公司等核心单位承办。大赛面向全球开发者、开源贡献者、高校科研团队、企业 AI 团队、科研机构、创业团队及 AI Builders，聚焦 AI 前沿项目发现、工程验证、开放协作与生态连接。 大赛以 “Open. Share. Build.” 为核心口号，围绕 新智基座（Agent Infra）、无界应用（Boundless Agents）、前沿探索（AI for Research）、具身未来（Embodied Future） 四大赛道展开，重点关注 AI 项目的工程可验证性、开放协作价值、真实场景价值和长期成长潜力，寻找具备可运行 Demo、可复用成果和真实应用潜力的 AI 创新项目。 大赛规划总奖金池为 500万元级现金激励，设有全场大奖、四大赛道冠亚季军及多个单项奖。其中，全场大奖奖金为 100万元。除现金奖励外，优秀团队还将有机会获得算力与云资源、导师辅导、技术社区曝光、产业场景对接、资本机构直达等多维度资源支持，助力优秀开源 AI 项目持续成长与落地转化。 大赛计划于7月21日在杭州云谷中心（杭州市西湖区灯彩街1009号）举行线下启动仪式。届时，组委会将围绕赛事机制、四大赛道、参赛路径、作品提交要求和评审方向进行集中解读，并同步开启作品提交通道。此后，大赛将在北京、上海、深圳、杭州、硅谷、新加坡等城市开展全球城市宣讲，面向四大赛道持续招募优秀团队。 按照赛程安排，7月16日大赛官网正式发布并开启报名通道，7月21日举行线下启动仪式，同步开放作品提交通道。7月下旬至8月中旬进入初赛作品提交及全球城市宣讲阶段；8月中旬至下旬开展初赛评审与复赛辅导；8月下旬至9月初进行复赛评审，遴选决赛队伍（各赛道具体安排以官网公布为准）。9月20日起启动决赛周预热，9月22日四大赛道决赛队伍将在杭州展开线下角逐，通过项目路演、Demo展示和专家答辩等环节评选最终奖项。9月23日举办“GOAI DAY”，集中呈现冠军项目Showtime、全场大奖评选及颁奖典礼，展示全球AI开源创新成果。 GOAI 世界人工智能开源大赛现已面向全球开","articleId":"","url":"https://infoq.cn/article/r3sAtSl97Gx5CuZHXOdi"}}