{"schemaVersion":"kfc_portal_schema_v1","generatedAt":"2026-07-24T16:05:28.460162+00:00","type":"news","id":"news_3f07ab9f8fe6ae820448","item":{"id":"news_3f07ab9f8fe6ae820448","type":"news","title":"特斯拉再次推迟robotaxi规模化，节点延至FSD v15","sourceId":"automotiveworld.com","status":"new","publishedAt":"2026-07-24T15:09:25","updatedAt":"2026-07-24T12:00:46.342044Z","summary":"特斯拉二季度财报会议显示，公司以软件承诺安抚投资者，但尚无车队或安全数据支撑。作者：Stewart Burnett。","articleId":"","url":"https://automotiveworld.com/analysis/tesla-once-again-defers-robotaxi-scale-this-time-to-fsd-v15"}}