{"schemaVersion":"kfc_portal_schema_v1","generatedAt":"2026-07-20T05:19:17.823322+00:00","type":"news","id":"news_49df61286d8c5d7677a6","item":{"id":"news_49df61286d8c5d7677a6","type":"news","title":"由于设备短缺迫在眉睫，韩美半导体加快 HBM 工具产量并种植美国国旗","sourceId":"digitimes.com","status":"selected_for_digest","publishedAt":"2026-07-20T08:01:41","updatedAt":"2026-07-20T04:57:55.957144Z","summary":"韩国韩美半导体 (Hanmi Semiconductor) 正在竞相扩大全球存储器和代工制造商用来制造高带宽存储器 (HBM) 的键合设备的产量，并警告说，从 2027 年起，需求可能会超过供应，这一瓶颈将波及目前由美光 (Micron)、SK 海力士 (SK Hynix) 和台积电 (TSMC) 等公司资助的人工智能芯片建设。","articleId":"","url":"https://digitimes.com/news/a20260717VL208/hanmi-hbm-usa-demand-equipment.html"}}