{"schemaVersion":"kfc_portal_schema_v1","generatedAt":"2026-07-21T00:23:54.567158+00:00","type":"news","id":"news_3ba057a1e10163bcee96","item":{"id":"news_3ba057a1e10163bcee96","type":"news","title":"Israel Innovation Authority Launches NIS 100 Million National Quantum Computing R&D Infrastructure","sourceId":"thequantuminsider.com","status":"new","publishedAt":"2026-07-20T19:47:24","updatedAt":"2026-07-20T23:40:02.732912Z","summary":"","articleId":"","url":"https://thequantuminsider.com/2026/07/20/israel-launches-national-quantum-computing-infrastructure"}}