{"schemaVersion":"kfc_portal_schema_v1","generatedAt":"2026-07-17T12:24:02.093720+00:00","type":"news","id":"news_256fd5d1ae612702b13f","item":{"id":"news_256fd5d1ae612702b13f","type":"news","title":"全球首个千亿参数级！中国气象局启动“风和”模型全球开源计划","sourceId":"ithome.com","status":"selected_for_digest","publishedAt":"2026-07-17T15:26:32","updatedAt":"2026-07-17T10:58:23.566131Z","summary":"IT之家 7 月 17 日消息，据央视新闻报道，7 月 17 日，在 2026 世界人工智能大会（WAIC）气象专会上，中国气象局发布 人工智能气象服务系统“风和”大语言模型，并启动“风和”全球开源计划 。 IT之家从报道获悉，此举旨在通过开放共享推动气象人工智能走向世界，服务全球防灾减灾合作与可持续发展，同时汇聚开发者、科研机构和国际伙伴共建生态。 “风和”是由中国气象局公共气象服务中心联合雄安人工智能创新研究院、智谱等单位研发的 全球首个千亿参数 级 开源气象大语言模型 ，能为天气分析研判、风险评估和气象服务提供智能支撑。基于地球系统数据资源基座，“风和”训练了 5000 万 tokens 高质量气象服务语料，集成权威气象数据，并已完成生成式人工智能的备案，为用户提供安全可控的模型应用。 当前，“风和”不仅为全国气象服务业务提供基础支撑，为国内公众提供个性化、智能化气象信息查询、气象服务建议和气象风险预警，也深度融入全球全民早期预警倡议，其国际版已上线并融入气象智能预警方案“妈祖”，为全球用户提供中英文智能问答、天气查询和风险分析服务。 随着“风和”全球开源计划的启动， 中国气象局已在 GitHub、Hugging Face 等平台开放完整模型权重，并同步开放标准化 API 接口、云服务以及定制化部署方案 ，构建开放共享的气象人工智能生态。这不仅是模型代码的开放，更是一套完整的技术交付方案，允许全球用户将“风和”嵌入具身智能、App、小程序等各类终端。 未来，依托“风和”的智能能力，海量气象数据能够快速转化为直观、易懂的风险产品，实现灾害风险的一键分析与评估； 复杂的预警信息能够转化为通俗易懂的自然语言交互服务，为公众提供更加精准的风险提示和避险建议； 同时结合交通、能源、电力、健康等行业场景，将预警信息进一步转化为可执行的行动方案。 从公众服务到专业研判，从风险识别到行动响应，“风和”正在让气象预警更加可理解、可获取、可行动，为全民早期预警体系建设提供智能支撑。","articleId":"","url":"https://ithome.com/0/978/082.htm"}}