{"schemaVersion":"kfc_portal_schema_v1","generatedAt":"2026-07-18T08:58:31.891580+00:00","type":"news","id":"news_b5eee276d187f3d944fd","item":{"id":"news_b5eee276d187f3d944fd","type":"news","title":"全球市值第一再次易主：苹果盘中登顶，英伟达收盘反超","sourceId":"163.com","status":"new","publishedAt":"2026-07-18T09:41:04","updatedAt":"2026-07-18T08:48:51.351427Z","summary":"7月18日消息，[苹果](https://tech.163.com/keywords/8/f/82f9679c/1.html)周五盘中一度以约4.88万亿美元的市值超过[英伟达](https://tech.163.com/keywords/8/f/82f14f1f8fbe/1.html)，短暂成为全球市值最高的公司。不过到当天[收盘](https://tech.163.com/keywords/6/3/653676d8/1.html)，英伟达重新回到第一位。 路透社报道苹果反超时，英伟达市值约为4.86万亿美元，两家公司只差约200亿美元。这个差距约占苹果市值的0.4%，[股价](https://tech.163.com/keywords/8/a/80a14ef7/1.html)稍有变化就可能改写排名。这也是苹果自2025年4月以来首次在盘中回到全球市值第一。 收盘行情显示，苹果报333.74美元，约涨0.14%；英伟达报202.81美元，约跌2.21%。按收盘后的行情估算，英伟达市值约4.95万亿美元，苹果约4.91万亿美元，英伟达领先约320亿美元。 苹果此前常被视为AI竞赛中的落后者。BRI Wealth Management投资主管托妮・梅多斯（Toni Meadows）对Reuters表示，市场对苹果的看法已经发生变化。与投入巨额资金建设模型和数据中心的公司相比，苹果的资本开支压力较小，还可以通过服务、设备生态和硬件升级获得收入。 英伟达仍是AI基础设施支出的主要受益者。Segal Marco Advisors副总裁本杰明・霍尔（Benjamin Hall）对路透社表示，两家公司短暂交换名次并没有实质区别，英伟达仍会是下一阶段AI发展的重要参与者。 苹果6月8日发布了Siri AI，新功能包括理解用户的个人情境、识别屏幕内容和调用更广泛的知识。苹果官方公告显示，目前新版Siri仍在开发者测试阶段，公开测试版计划于2026年晚些时候提供，尚未面向所有用户全面推出。（易句） （本文由AI翻译，网易编辑负责校对）","articleId":"","url":"https://163.com/tech/article/L242H33U00097U7T.html"}}