{"schemaVersion":"kfc_portal_schema_v1","generatedAt":"2026-07-18T18:54:31.097960+00:00","type":"news","id":"news_c7fdcee2d7fa50b9b656","item":{"id":"news_c7fdcee2d7fa50b9b656","type":"news","title":"Intuit 在四个月内两次废弃了自己的人工智能代理架构。在 VB Transform 2026 上，其 AI 副总裁称这是快速路径","sourceId":"venturebeat.com","status":"digested","publishedAt":"2026-07-18T04:46:55","updatedAt":"2026-07-19T01:10:12.034286+08:00","summary":"Intuit 是代理人工智能应用的早期先驱，但它的成功之路并不是一条直线。在 VB Transform 2026 上，AI Nhung Ho 的 Intuit 副总裁描述了该公司如何在大约四个月的时间内两次重建其代理架构，首先从一组专业代理迁移到中央编排层，然后在编排器本身开始出现故障时放弃该层，转而采用基于技能和工具的系统在其自身的复杂性之下。完整的第二次重建花了 60 天，第一个工作版本不到 20 天。强制第二次重写的故障模式是特定的。编排系统中的代理以自然语言相互传递结果，每次切换都会丢失下一个代理正确操作所需的上下文。 “如果你有 10 名特工，而且他们都在互相传球，那么每次传球发生时，错误就会复合，”Ho 说。为什么编排层崩溃 Ho 表示，最初推动专业代理的动力来自于一个简单的客户投诉。客户仍然需要管理一批有能力的代理，以决定使用哪个代理来执行哪个任务。 Intuit 的答案是一个可以执行任务并执行任务的系统","articleId":"news_c7fdcee2d7fa50b9b656","url":"https://venturebeat.com/orchestration/intuit-scrapped-its-own-ai-agent-architecture-twice-in-four-months-at-vb-transform-2026-its-ai-vp-called-that-the-fast-path"}}