{"schemaVersion":"kfc_portal_schema_v1","generatedAt":"2026-07-24T07:05:19.939091+00:00","type":"news","id":"news_29343a15949504dd8587","item":{"id":"news_29343a15949504dd8587","type":"news","title":"Robinhood 首席执行官 X 账号遭黑客攻击以推广疑似 memecoin 骗局","sourceId":"cointelegraph.com","status":"new","publishedAt":"2026-07-24T02:09:26","updatedAt":"2026-07-24T02:35:37.749268Z","summary":"据报道，黑客接管了 Robinhood 首席执行官 Vlad Tenev 的 X 账号，推广一款名为「VLAD」的假 memecoin，并发布了疑似恶意代币合约地址。周四，在出现一篇推广「VLAD」假 memecoin 并附带疑似恶意代币合约地址的帖子后，一名或多名黑客接管了 Tenev 的 X 账号。该帖在不到 20 分钟内获得超过 17.5 万次浏览，随后用户识破骗局并警告他人不要与该代币互动。","articleId":"","url":"https://cointelegraph.com/news/robinhood-ceo-x-account-hacked-in-apparent-memecoin-scam"}}