{"schemaVersion":"kfc_portal_schema_v1","generatedAt":"2026-07-21T10:39:33.511233+00:00","type":"news","id":"news_53cca83ffdfa6f8dd780","item":{"id":"news_53cca83ffdfa6f8dd780","type":"news","title":"中国银行将推长城 BOC-AI 信用卡，每月消费达标有机会领取智谱、MiniMax 等 Token 权益","sourceId":"ithome.com","status":"new","publishedAt":"2026-07-21T17:28:06","updatedAt":"2026-07-21T10:38:58.226375Z","summary":"IT之家 7 月 21 日消息，中国银行上周（7 月 17 日）宣布，长城 BOC-AI 信用卡即将上线。 IT之家从“中国银行信用卡”公众号了解到，这款信用卡开卡达标、每月消费达标后， 有机会领取智谱清言、MiniMax、阿里 Qoder 或腾讯 WorkBuddy 等 AI 产品的月度会员及 Token 权益 。 同时，该卡的卡组织为中国银联，等级为金卡，从宣传图上的“无界卡”可以看出，该卡预计将支持仅申领数字卡。 此外，该产品计划于本月底上线，具体发布时间、产品和活动内容需以正式发布为准。","articleId":"","url":"https://ithome.com/0/979/690.htm"}}