{"schemaVersion":"kfc_portal_schema_v1","generatedAt":"2026-07-24T10:05:20.882010+00:00","type":"news","id":"news_daad5e20bcded0268efc","item":{"id":"news_daad5e20bcded0268efc","type":"news","title":"可口可乐品牌重塑意外契合Z世代「冰箱香烟」梗：「在人们熟知和喜爱的事物上做延伸」","sourceId":"fortune.com","status":"new","publishedAt":"2026-07-24T05:50:05","updatedAt":"2026-07-24T04:46:24.482965Z","summary":"Metaforce咨询顾问艾伦·亚当森表示：「字体不等于品牌。」与此同时，Z世代正让各种梗疯狂传播。","articleId":"","url":"https://fortune.com/2026/07/23/what-is-fridge-cigarette-coca-cola-marlboro-font-rebrand"}}