{"schemaVersion":"kfc_portal_schema_v1","generatedAt":"2026-07-17T09:09:44.629337+00:00","type":"news","id":"news_9551d70497fa91fc7bff","item":{"id":"news_9551d70497fa91fc7bff","type":"news","title":"富士通联手发那科、安川和川崎开发物理人工智能","sourceId":"securitybrief.asia","status":"new","publishedAt":"2026-07-17T10:29:00","updatedAt":"2026-07-17T07:19:12.434212Z","summary":"劳动力短缺和劳动力老龄化正促使日本制造商在工厂、物流和医院测试人工智能控制的机器人。","articleId":"","url":"https://securitybrief.asia/story/fujitsu-joins-fanuc-yaskawa-kawasaki-on-physical-ai"}}