{"schemaVersion":"kfc_portal_schema_v1","generatedAt":"2026-07-24T17:15:31.178086+00:00","type":"news","id":"news_83ec75c7a6103a9ca18e","item":{"id":"news_83ec75c7a6103a9ca18e","type":"news","title":"剑桥科技：拟出资8亿元参设基金","sourceId":"36kr.com","status":"new","publishedAt":"2026-07-24T20:08:22","updatedAt":"2026-07-24T16:11:18.798979Z","summary":"36氪获悉，剑桥科技公告，公司于7月24日签订了《嘉兴沪江光电产业基金合伙企业（有限合伙）之合伙协议》，公司拟作为有限合伙人以自有资金8亿元参与投资嘉兴沪江光电产业基金合伙企业（有限合伙）（简称「合伙基金」），占比99.9988%。合伙基金主要投资于集成电路、人工智能等先进制造、信息技术类新兴行业的未上市企业股权（重点聚焦光器件、芯片及核心IC领域企业）。","articleId":"","url":"https://36kr.com/newsflashes/3909597634893193"}}