{"schemaVersion":"kfc_portal_schema_v1","generatedAt":"2026-07-16T16:18:39.182708+00:00","type":"news","id":"news_355a279ddc4e098bdcac","item":{"id":"news_355a279ddc4e098bdcac","type":"news","title":"人工智能转向边缘的受监管实时系统","sourceId":"securitybrief.asia","status":"new","publishedAt":"2026-07-16T08:30:00","updatedAt":"2026-07-16T16:18:34.651309Z","summary":"随着企业将自主人工智能从试点推向整个亚太地区的实时边缘系统，治理差距正在出现。","articleId":"","url":"https://securitybrief.asia/story/ai-shifts-to-governed-real-time-systems-at-the-edge"}}