{"schemaVersion":"kfc_portal_schema_v1","generatedAt":"2026-07-20T13:49:17.461296+00:00","type":"news","id":"news_0bf62579d88de68495c5","item":{"id":"news_0bf62579d88de68495c5","type":"news","title":"纽约数据中心建设暂停令：摩擦阻碍经济增长","sourceId":"bloomberg.com","status":"new","publishedAt":"2026-07-20T18:47:10","updatedAt":"2026-07-20T13:48:46.419471Z","summary":"纽约数据中心暂停：摩擦减缓经济增长","articleId":"","url":"https://bloomberg.com/opinion/articles/2026-07-20/new-york-data-center-moratorium-friction-slows-economic-growth"}}