{"schemaVersion":"kfc_portal_schema_v1","generatedAt":"2026-07-24T06:05:19.045297+00:00","type":"news","id":"news_60ba735d254a94a5a2d0","item":{"id":"news_60ba735d254a94a5a2d0","type":"news","title":"近 6 年首次未用自家 ISOCELL，曝三星 Galaxy S27/S27+ 手机主摄配索尼 5000 万传感器","sourceId":"ithome.com","status":"new","publishedAt":"2026-07-24T11:05:14","updatedAt":"2026-07-24T06:00:19.370059Z","summary":"荷兰科技媒体Galaxy Club爆料，三星Galaxy S27和Galaxy S27+主摄将采用5000万像素索尼传感器，而非三星自家ISOCELL传感器，这将是近年来三星Galaxy S旗舰系列首次使用索尼传感器。三星Galaxy S系列主摄使用索尼传感器可追溯至2020年发布的Galaxy S20系列。超广角方面，Galaxy S27和S27+预计沿用1200万像素、F2.2光圈方案，Galaxy S27 Pro和Galaxy S27 Ultra则将采用5000万像素。","articleId":"","url":"https://ithome.com/0/980/995.htm"}}