{"schemaVersion":"kfc_portal_schema_v1","generatedAt":"2026-07-21T06:17:26.532856+00:00","type":"article","id":"md_0d70fe8bc8385f473724","item":{"id":"md_0d70fe8bc8385f473724","type":"article","title":"微软CEO Satya Nadella新长文：反向信息悖论，新的“便利论”？","sourceId":"mp.weixin.qq.com","status":"digested","publishedAt":"2026-07-15T17:15:58+08:00","updatedAt":"2026-07-15T09:16:38Z","summary":"大模型时代，同样的事在重演，只不过喂给模型的不是你的注意力，是你公司的核心知识。 微软 CEO Satya Nadella 刚刚发了篇长文，提了个概念： 反向信息悖论（The Reverse Information Paradox） 。 诺贝尔经济学奖得主 Kenneth Arrow 说过一个经典困境：信息的价值在买家得到它之前无从知晓，但一旦知道了，就等于免费到手了。卖信息的人面临一个死结，为了卖，得先露。 AI 把这个困境翻了过来。 Nadella 说，现在用 AI 的企业才是那个冒着泄漏风险的人。你付了两次费：一次是钱，一次是你喂给模型的专有知识。模型表现越好，说明你喂得越多。信息不对称慢慢倾斜，模型提供商越来越懂你，你却不知","path":"data/semantic_pipeline_v2/articles/md_0d70fe8bc8385f473724/raw.md","url":"https://mp.weixin.qq.com/s/TI1PhbO1xm455-WEOBGi2Q"}}