{"schemaVersion":"kfc_portal_schema_v1","generatedAt":"2026-07-24T04:27:15.542010+00:00","type":"article","id":"md_32c08a67c358e1c03775","item":{"id":"md_32c08a67c358e1c03775","type":"article","title":"网易有道CEO周枫：一张图，七个要点，读懂“Harness思维”","sourceId":"mp.weixin.qq.com","status":"digested","publishedAt":"2026-07-02T16:00:43Z","updatedAt":"2026-07-02T16:03:13Z","summary":"作者 | 周枫 审校 | 凌敏 转载来源 | 周枫（ID：youdaozhoufeng） 关于 Harness/Agent 的讨论比较多，总体上大家共同的看法是：现在是通过 Harness 来做大模型创新应用的好时机，但是 Harness 和以往的应用开发范式有较大不同，需要用一些不同的方法，才能做出好的产品，沿用原有的思维方式可能事倍功半。 本文从行业分享和内部实战中总结了一些最佳实践，和大家探讨。 先界定一下概念。所谓 Harness（马具 / 载体），指的是模型之外、把模型包装成一个可用产品的那一整层工程：上下文管理、工具、记忆、持久化状态、评测、循环控制、可观测性与权限治理。 一个标准的说法是 Agent = Model +","path":"data/semantic_pipeline_v2/articles/md_32c08a67c358e1c03775/raw.md","url":"https://mp.weixin.qq.com/s/x68qt7DJnEIvRD2bycHk4w"}}