{"schemaVersion":"kfc_portal_schema_v1","generatedAt":"2026-07-22T00:39:36.243345+00:00","type":"article","id":"md_89a92d5968504fa2b43f","item":{"id":"md_89a92d5968504fa2b43f","type":"article","title":"写给所有“控制狂领导”","sourceId":"mp.weixin.qq.com","status":"digested","publishedAt":"2026-06-14T13:36:47Z","updatedAt":"2026-06-14T13:43:03Z","summary":"职场上有一类领导让人头皮发麻：控制狂。 为什么发麻？因为在他们眼里，没有一件事儿不该管。 他们事无巨细。二十页报告，他会花俩小时纠正字体大小、对齐方式。 他们极度缺乏安全感。无法容忍任何一分钟信息真空，必须随时报告进度，把下属像提线木偶一样攥在手里。 最烦的是，他们经常自己都不清楚自己要什么。做海报你问他要什么风格，他说“你先做，要大气、高级、有网感”。你熬夜赶出三个版本，他也说不出哪里不对，只会让你再来三个。 为什么会这样？我最近有种感觉，一个根本原因，是他们没有能力分清三个重要概念： 标准、风格、习惯。 好的管理，是“死守标准、传授风格、少管习惯”。 01 标准：不可协商的规则 标准，是那些“不可协商的规则”。 划重点，它不是“","path":"data/semantic_pipeline_v2/articles/md_89a92d5968504fa2b43f/raw.md","url":"https://mp.weixin.qq.com/s/GfTgq5c3Tzz43THf2dFXAg"}}