{"schemaVersion":"kfc_portal_schema_v1","generatedAt":"2026-07-16T07:51:54.463718+00:00","type":"article","id":"md_a9aebc89e3f758de0c95","item":{"id":"md_a9aebc89e3f758de0c95","type":"article","title":"硅谷深陷算力荒：H200一夜涨价30%，H100抢到缺货，Karpathy也未能幸免","sourceId":"local_article","status":"digested","publishedAt":"2026-06-14T17:04:43Z","updatedAt":"2026-06-14T17:06:27Z","summary":"url: https://mp.weixin.qq.com/s/MDiEt2PfdPTu5GBqiAT4Ig [p001] [p002] [p003] 作者 ｜ 四月 [p004] 2026 年 5 月的硅谷，对于 AI 算力的“饥荒”和焦虑，正达到一个前所未有的高度。 [p005] 哪怕那些站在算力中心的人，也不得不开始为算力排队。 [p006] 在英伟达，负责应用深度学习研究团队的 Bryan Catanzaro 找黄仁勋申请训练卡。最近大家一直抱怨卡不够用，受限太多。 [p007] “不好意思，那些卡已经卖掉了”，这是老黄给出的回复。 [p008] Catanzaro 是英伟达的大功臣。十多年前，正是他留意到，GPU 迎来了首","path":"data/semantic_pipeline_v2/articles/md_a9aebc89e3f758de0c95/raw.md","url":""}}