{"schemaVersion":"kfc_portal_schema_v1","generatedAt":"2026-07-20T00:47:53.001010+00:00","type":"article","id":"md_bc0875aee0797933d19d","item":{"id":"md_bc0875aee0797933d19d","type":"article","title":"“Token”必须死？","sourceId":"mp.weixin.qq.com","status":"digested","publishedAt":"2026-06-11T16:34:22Z","updatedAt":"2026-06-11T16:35:12Z","summary":"本文为《Token经济学》系列第九期。当所有人都在用token丈量AI的价值时，两篇几乎同时发表的论文提出了一个更根本的问题：语言生成的核心计算，是否必须发生在token空间里？ 文｜晓静 编辑｜徐青阳 “我语言的局限，即意味着我世界的局限。”（ Die Grenzen meiner Sprache bedeuten die Grenzen meiner Welt. ） 哲学家维特根斯坦在1921年写下这句话时，他谈论的是人类认知的边界。一百年后，这句话精确地描述了大语言模型面临的结构性困境，如果AI的“语言”就是离散token序列，那么它的“世界”永远被困在token能表达的范围内。 这也引出了一个老生常谈的问题：大语言模型范式能","path":"data/semantic_pipeline_v2/articles/md_bc0875aee0797933d19d/raw.md","url":"https://mp.weixin.qq.com/s/lvZ1kpAJwutRFGMyks7DyQ"}}