{"schemaVersion":"kfc_portal_schema_v1","generatedAt":"2026-07-16T09:04:53.445313+00:00","type":"article","id":"md_df01f4bb627c9f7d3810","item":{"id":"md_df01f4bb627c9f7d3810","type":"article","title":"踩着物理AI的风口，Momenta冲刺IPO-124e75330e","sourceId":"local_article","status":"digested","publishedAt":"2026-07-02T03:24:25Z","updatedAt":"2026-07-02T03:31:09Z","summary":"如果你想第一时间看到我们的文章 就把 ☆星标☆ 点起来吧 来源 | 伯虎财经（bohuFN）作者 | 楷楷 物理 AI，成了各个行业争相追逐的热点。 近日，英伟达CEO黄仁勋在COMPUTEX演讲中强调：“物理AI是AI的下一波浪潮” 。过去一年，马斯克、吴泳铭、李飞飞等行业巨擘纷纷聚焦这一概念，物理AI正成为业界共识。 踏入2026年，物理AI的热度更上一层楼。自动驾驶独角兽Momenta恰好踩着这一风口，冲到了港交所门前，计划于7月8日正式挂牌上市。 而且，这次发行没有设置价格区间，而是直接锁定了最终发行价，足见Momenta的火爆程度，市场更顺势给它贴上了“物理AI第一股”的标签。 但耐人寻味的是，就在Momenta冲向“物理","path":"data/semantic_pipeline_v2/articles/md_df01f4bb627c9f7d3810/raw.md","url":""}}