{"schemaVersion":"kfc_portal_schema_v1","generatedAt":"2026-07-20T14:49:14.544371+00:00","type":"article","id":"news_32e42f557addb96bac31","item":{"id":"news_32e42f557addb96bac31","type":"article","title":"三星和 SK 海力士竞相在四年内让光州存储中心投入运营","sourceId":"digitimes.com","status":"digested","publishedAt":"2026-07-16T09:17:57","updatedAt":"2026-07-18T07:07:58Z","summary":"Samsung Electronics and SK hynix are set to anchor a KRW800 trillion (US$532.4 billion) semiconductor cluster at the former Gwangju military airport site in South Korea. Industry experts describe the project as a race against time, with an ambitious target of bringing four fabrication plants online within four years. W","path":"data/semantic_pipeline_v2/articles/news_32e42f557addb96bac31/raw.md","url":"https://digitimes.com/news/a20260713PD213/samsung-infrastructure-water-industrial-government.html"}}