{"schemaVersion":"kfc_portal_schema_v1","generatedAt":"2026-07-19T21:54:18.530311+00:00","type":"article","id":"news_e085ec4af6be45223de4","item":{"id":"news_e085ec4af6be45223de4","type":"article","title":"Momenta靠什么站上物理AI的「青藏高原」？","sourceId":"leiphone.com","status":"digested","publishedAt":"2026-07-17T17:43:00","updatedAt":"2026-07-17T18:45:41Z","summary":"什么样的公司，能让奔驰、比亚迪这些大车企在同一张基石股权的认购单上签字？ 2026年7月8日，Momenta将在港交所上市，IPO募资58.9亿港元，新加坡GIC、富达国际、奔驰、比亚迪、贝莱德等14家基石投资者吃掉近一半发售股份。 新加坡主权基金和德系豪华车品牌、中国新能源霸主站在同一张认购单上，这种局面在港股科技IPO史上并不多见。 更引人注目的是Momenta被贴上的标签：“物理AI第一股”。 数字AI的壁垒建立在算力和语料上，互联网积累了海量文本，只要算力管够、工程到位，就能训出能写会聊的模型。 物理AI的壁垒建立在物理世界上，互联网没有积累过真实的刹车距离、路面摩擦力和人类司机的应急反应，这些数据只能靠一辆辆量产车一公里一","path":"data/semantic_pipeline_v2/articles/news_e085ec4af6be45223de4/raw.md","url":"https://leiphone.com/category/transportation/8ThXFb3eG8jEKzmZ.html"}}