{"schemaVersion":"kfc_portal_schema_v1","generatedAt":"2026-07-20T04:31:05.495525+00:00","type":"article","id":"news_854c81132b35aa0ae2ef","item":{"id":"news_854c81132b35aa0ae2ef","type":"article","title":"印度综述：随着当地生态系统扩展到晶圆厂和组装之外，印度加深了半导体和人工智能的雄心","sourceId":"digitimes.com","status":"failed","publishedAt":"2026-07-20T08:01:23","updatedAt":"2026-07-20T02:41:08Z","summary":"India is broadening its technology strategy from attracting chip factories to building semiconductor equipment, materials, AI capabilities, supply chains and trade partnerships as it seeks a larger role in global electronics.","path":"data/semantic_pipeline_v2/articles/news_854c81132b35aa0ae2ef/raw.md","url":"https://digitimes.com/news/a20260717VL205/india-roundup-applied-materials-electronics-equipment-hp-subsidies.html"}}