{"schemaVersion":"kfc_portal_schema_v1","generatedAt":"2026-07-18T01:09:19.539425+00:00","type":"issue","id":"ic_skipped_non_ai_top_level_ontology_interoperability","item":{"id":"ic_skipped_non_ai_top_level_ontology_interoperability","type":"issue","title":"ic_skipped_non_ai_top_level_ontology_interoperability","topicId":"{skipped_non_ai}","status":"skipped_non_ai","sourceArticleCount":null,"updatedAt":null,"createdAt":null,"canonicalQuestion":"","path":"data/semantic_pipeline_v2/index/issue_cards/{skipped_non_ai}/ic_skipped_non_ai_top_level_ontology_interoperability.md","mtime":"2026-06-13T02:10:25.047762+00:00","html":"<h1 id=\"skipped-article-non-ai-metadata-only\">Skipped Article (Non-AI / Metadata Only)</h1>\n<h2 id=\"_1\">基本信息</h2>\n<ul>\n<li>\n<p><strong>文章编号：</strong> md_1d563e81096b4870ba75</p>\n</li>\n<li>\n<p><strong>标题：</strong> 本体论（八）：顶层本体</p>\n</li>\n<li>\n<p><strong>状态：</strong> skipped_non_ai</p>\n</li>\n<li>\n<p><strong>原因：</strong> AI centrality below threshold; ontology engineering and semantic interoperability is treated as general knowledge systems rather than AI-driven mechanism</p>\n</li>\n</ul>\n<h2 id=\"one-line-summary\">One-line Summary</h2>\n<p>顶层本体用于统一不同系统的语义结构，但会增加抽象建模成本与复杂度。</p>\n<h2 id=\"possible-ai-link-weak\">Possible AI Link (Weak)</h2>\n<p>可作为未来AI知识图谱、语义层Agent系统的底层建模参考，但非AI主驱动议题。</p>","text":"Skipped Article (Non-AI / Metadata Only) 基本信息 文章编号： md_1d563e81096b4870ba75 标题： 本体论（八）：顶层本体 状态： skipped_non_ai 原因： AI centrality below threshold; ontology engineering and semantic interoperability is treated as general knowledge systems rather than AI-driven mechanism One-line Summary 顶层本体用于统一不同系统的语义结构，但会增加抽象建模成本与复杂度。 Possible AI Link (Weak) 可作为未来AI知识图谱、语义层Agent系统的底层建模参考，但非AI主驱动议题。"}}